spid_compliant_certificates/__init__.py
spid_compliant_certificates/commons/__init__.py
spid_compliant_certificates/commons/logger.py
spid_compliant_certificates/generator/__init__.py
spid_compliant_certificates/generator/generate.py
spid_compliant_certificates/validator/__init__.py
spid_compliant_certificates/validator/report.py
spid_compliant_certificates/validator/utils.py
spid_compliant_certificates/validator/validate.py
spid_compliant_certificates/validator/checks/__init__.py
spid_compliant_certificates/validator/checks/basic_constraints.py
spid_compliant_certificates/validator/checks/certificate_policies.py
spid_compliant_certificates/validator/checks/custom_oid.py
spid_compliant_certificates/validator/checks/digest_algorithm.py
spid_compliant_certificates/validator/checks/key_type_and_size.py
spid_compliant_certificates/validator/checks/key_usage.py
spid_compliant_certificates/validator/checks/subject_dn.py
spid_compliant_certificates/validator/checks/time_validity.py
spid_compliant_certificates/validator/test_cases/__init__.py
spid_compliant_certificates/validator/test_cases/base.py
spid_compliant_certificates/validator/test_cases/private_sector.py
spid_compliant_certificates/validator/test_cases/public_sector.py
spid_compliant_certificates-0.5.5.data/scripts/spid-compliant-certificates
spid_compliant_certificates-0.5.5.dist-info/LICENSE
spid_compliant_certificates-0.5.5.dist-info/METADATA
spid_compliant_certificates-0.5.5.dist-info/WHEEL
spid_compliant_certificates-0.5.5.dist-info/top_level.txt
spid_compliant_certificates-0.5.5.dist-info/RECORD
