Metadata-Version: 2.1
Name: spid_compliant_certificates
Version: 0.5.5
Summary: Generate X509 certificates according to Avviso SPID 29 v3
Home-page: https://github.com/italia/spid-compliant-certificates-python
Author: Paolo Smiraglia
Author-email: paolo.smiraglia@gmail.com
License: MIT
Platform: UNKNOWN
Requires-Python: >=3.6
